{"name":"Frbr","body":"FRBR\r\n====\r\n\r\nFRBRlize script and cgi toolFRBR-Entry version 0.01\r\n=======================\r\n\r\nThe README is used to introduce the module and provide instructions on\r\nhow to install the module, any machine dependencies it may have (for\r\nexample C compilers and installed libraries) and any other information\r\nthat should be provided before the module is installed.\r\n\r\nA README file is required for CPAN modules since CPAN extracts the\r\nREADME file from a module distribution so that people browsing the\r\narchive can use it get an idea of the modules uses. It is usually a\r\ngood idea to provide version information here so that people can\r\ndecide whether fixes for the module are worth downloading.\r\n\r\nINSTALLATION\r\n\r\nTo install this module type the following:\r\n\r\n   perl Makefile.PL\r\n   make\r\n   make test\r\n   make install\r\n\r\nDEPENDENCIES\r\n\r\nThis module requires these other modules and libraries:\r\n\r\n  blah blah blah\r\n\r\nCOPYRIGHT AND LICENCE\r\n\r\nPut the correct copyright and licence information here.\r\n\r\nCopyright (C) 2011 by thomas\r\n\r\nThis library is free software; you can redistribute it and/or modify\r\nit under the same terms as Perl itself, either Perl version 5.10.0 or,\r\nat your option, any later version of Perl 5 you may have available.\r\n\r\n\r\n","tagline":"FRBRlize script and cgi tool","google":"","note":"Don't delete this file! It's used internally to help with page regeneration."}